{"/Users/davorsercer/Library/CloudStorage/Dropbox/Code/rust/dsa/my_code/v6_mutability/src/main.rs":{"items":[{"fn_id":12,"basic_blocks":[{"statements":[{"type":"assign","target_local":{"id":4,"fn_id":12},"range":{"from":66,"until":78},"rval":{"type":"borrow","target_local":{"id":1,"fn_id":12},"range":{"from":66,"until":78},"mutable":false,"outlive":null}},{"type":"assign","target_local":{"id":3,"fn_id":12},"range":{"from":66,"until":78},"rval":{"type":"borrow","target_local":{"id":4,"fn_id":12},"range":{"from":66,"until":78},"mutable":false,"outlive":null}}],"terminator":{"type":"call","destination_local":{"id":2,"fn_id":12},"fn_span":{"from":66,"until":78}}},{"statements":[{"type":"assign","target_local":{"id":7,"fn_id":12},"range":{"from":84,"until":92},"rval":{"type":"borrow","target_local":{"id":1,"fn_id":12},"range":{"from":84,"until":92},"mutable":false,"outlive":null}},{"type":"assign","target_local":{"id":6,"fn_id":12},"range":{"from":84,"until":92},"rval":{"type":"borrow","target_local":{"id":7,"fn_id":12},"range":{"from":84,"until":92},"mutable":false,"outlive":null}}],"terminator":{"type":"call","destination_local":{"id":5,"fn_id":12},"fn_span":{"from":84,"until":92}}},{"statements":[{"type":"assign","target_local":{"id":0,"fn_id":12},"range":{"from":38,"until":43},"rval":null}],"terminator":{"type":"drop","local":{"id":2,"fn_id":12},"range":{"from":42,"until":43}}},{"statements":[],"terminator":{"type":"other"}},{"statements":[],"terminator":{"type":"drop","local":{"id":2,"fn_id":12},"range":{"from":42,"until":43}}},{"statements":[],"terminator":{"type":"other"}}],"decls":[{"type":"other","local":{"id":0,"fn_id":12},"ty":"Person","lives":[{"from":42,"until":43}],"shared_borrow":[],"mutable_borrow":[],"drop":false,"drop_range":[],"must_live_at":[]},{"type":"user","local":{"id":1,"fn_id":12},"name":"self","span":{"from":38,"until":43},"ty":"&Person","lives":[{"from":66,"until":78},{"from":84,"until":92}],"shared_borrow":[],"mutable_borrow":[],"drop":false,"drop_range":[],"must_live_at":[]},{"type":"other","local":{"id":2,"fn_id":12},"ty":"std::string::String","lives":[{"from":77,"until":78},{"from":84,"until":92},{"from":38,"until":43}],"shared_borrow":[],"mutable_borrow":[],"drop":true,"drop_range":[{"from":77,"until":78},{"from":84,"until":92},{"from":42,"until":43}],"must_live_at":[]},{"type":"other","local":{"id":3,"fn_id":12},"ty":"&std::string::String","lives":[{"from":66,"until":78}],"shared_borrow":[],"mutable_borrow":[],"drop":false,"drop_range":[],"must_live_at":[]},{"type":"other","local":{"id":4,"fn_id":12},"ty":"&std::string::String","lives":[{"from":66,"until":78}],"shared_borrow":[],"mutable_borrow":[],"drop":false,"drop_range":[],"must_live_at":[]},{"type":"other","local":{"id":5,"fn_id":12},"ty":"i32","lives":[{"from":91,"until":92},{"from":38,"until":43}],"shared_borrow":[],"mutable_borrow":[],"drop":false,"drop_range":[],"must_live_at":[]},{"type":"other","local":{"id":6,"fn_id":12},"ty":"&i32","lives":[{"from":84,"until":92}],"shared_borrow":[],"mutable_borrow":[],"drop":false,"drop_range":[],"must_live_at":[]},{"type":"other","local":{"id":7,"fn_id":12},"ty":"&i32","lives":[{"from":84,"until":92}],"shared_borrow":[],"mutable_borrow":[],"drop":false,"drop_range":[],"must_live_at":[]}]},{"fn_id":10,"basic_blocks":[{"statements":[{"type":"assign","target_local":{"id":3,"fn_id":10},"range":{"from":31,"until":36},"rval":{"type":"borrow","target_local":{"id":2,"fn_id":10},"range":{"from":31,"until":36},"mutable":true,"outlive":null}},{"type":"assign","target_local":{"id":5,"fn_id":10},"range":{"from":31,"until":36},"rval":null},{"type":"assign","target_local":{"id":4,"fn_id":10},"range":{"from":31,"until":36},"rval":{"type":"borrow","target_local":{"id":5,"fn_id":10},"range":{"from":31,"until":36},"mutable":false,"outlive":null}},{"type":"assign","target_local":{"id":7,"fn_id":10},"range":{"from":66,"until":78},"rval":null},{"type":"assign","target_local":{"id":6,"fn_id":10},"range":{"from":66,"until":78},"rval":{"type":"borrow","target_local":{"id":7,"fn_id":10},"range":{"from":66,"until":78},"mutable":false,"outlive":null}},{"type":"assign","target_local":{"id":10,"fn_id":10},"range":{"from":66,"until":78},"rval":{"type":"borrow","target_local":{"id":1,"fn_id":10},"range":{"from":66,"until":78},"mutable":false,"outlive":null}},{"type":"assign","target_local":{"id":9,"fn_id":10},"range":{"from":66,"until":78},"rval":{"type":"borrow","target_local":{"id":10,"fn_id":10},"range":{"from":66,"until":78},"mutable":false,"outlive":null}},{"type":"assign","target_local":{"id":8,"fn_id":10},"range":{"from":66,"until":78},"rval":null},{"type":"assign","target_local":{"id":12,"fn_id":10},"range":{"from":84,"until":92},"rval":null},{"type":"assign","target_local":{"id":11,"fn_id":10},"range":{"from":84,"until":92},"rval":{"type":"borrow","target_local":{"id":12,"fn_id":10},"range":{"from":84,"until":92},"mutable":false,"outlive":null}},{"type":"assign","target_local":{"id":16,"fn_id":10},"range":{"from":84,"until":92},"rval":{"type":"borrow","target_local":{"id":1,"fn_id":10},"range":{"from":84,"until":92},"mutable":false,"outlive":null}},{"type":"assign","target_local":{"id":15,"fn_id":10},"range":{"from":84,"until":92},"rval":{"type":"borrow","target_local":{"id":16,"fn_id":10},"range":{"from":84,"until":92},"mutable":false,"outlive":null}},{"type":"assign","target_local":{"id":14,"fn_id":10},"range":{"from":84,"until":92},"rval":{"type":"borrow","target_local":{"id":15,"fn_id":10},"range":{"from":84,"until":92},"mutable":false,"outlive":null}},{"type":"assign","target_local":{"id":13,"fn_id":10},"range":{"from":84,"until":92},"rval":null}],"terminator":{"type":"call","destination_local":{"id":0,"fn_id":10},"fn_span":{"from":31,"until":36}}},{"statements":[],"terminator":{"type":"other"}},{"statements":[],"terminator":{"type":"other"}}],"decls":[{"type":"other","local":{"id":0,"fn_id":10},"ty":"std::result::Result<(), std::fmt::Error>","lives":[{"from":35,"until":36}],"shared_borrow":[],"mutable_borrow":[],"drop":false,"drop_range":[],"must_live_at":[]},{"type":"user","local":{"id":1,"fn_id":10},"name":"self","span":{"from":31,"until":36},"ty":"&Person","lives":[{"from":31,"until":36},{"from":66,"until":78},{"from":84,"until":92}],"shared_borrow":[],"mutable_borrow":[],"drop":false,"drop_range":[],"must_live_at":[]},{"type":"user","local":{"id":2,"fn_id":10},"name":"f","span":{"from":31,"until":36},"ty":"&mut std::fmt::Formatter<'_>","lives":[{"from":31,"until":36}],"shared_borrow":[],"mutable_borrow":[{"from":31,"until":36},{"from":66,"until":78},{"from":84,"until":92}],"drop":false,"drop_range":[],"must_live_at":[{"from":31,"until":36},{"from":66,"until":78},{"from":84,"until":92}]},{"type":"other","local":{"id":3,"fn_id":10},"ty":"&mut std::fmt::Formatter<'_>","lives":[{"from":31,"until":36},{"from":66,"until":78},{"from":84,"until":92}],"shared_borrow":[],"mutable_borrow":[],"drop":false,"drop_range":[],"must_live_at":[]},{"type":"other","local":{"id":4,"fn_id":10},"ty":"&str","lives":[{"from":66,"until":78},{"from":84,"until":92},{"from":31,"until":36}],"shared_borrow":[],"mutable_borrow":[],"drop":false,"drop_range":[],"must_live_at":[]},{"type":"other","local":{"id":5,"fn_id":10},"ty":"&str","lives":[{"from":31,"until":36}],"shared_borrow":[],"mutable_borrow":[],"drop":false,"drop_range":[],"must_live_at":[]},{"type":"other","local":{"id":6,"fn_id":10},"ty":"&str","lives":[{"from":66,"until":78},{"from":84,"until":92},{"from":31,"until":36}],"shared_borrow":[],"mutable_borrow":[],"drop":false,"drop_range":[],"must_live_at":[]},{"type":"other","local":{"id":7,"fn_id":10},"ty":"&str","lives":[{"from":66,"until":78}],"shared_borrow":[],"mutable_borrow":[],"drop":false,"drop_range":[],"must_live_at":[]},{"type":"other","local":{"id":8,"fn_id":10},"ty":"&dyn std::fmt::Debug","lives":[{"from":77,"until":78},{"from":84,"until":92},{"from":31,"until":36}],"shared_borrow":[],"mutable_borrow":[],"drop":false,"drop_range":[],"must_live_at":[]},{"type":"other","local":{"id":9,"fn_id":10},"ty":"&std::string::String","lives":[{"from":66,"until":78}],"shared_borrow":[],"mutable_borrow":[],"drop":false,"drop_range":[],"must_live_at":[]},{"type":"other","local":{"id":10,"fn_id":10},"ty":"&std::string::String","lives":[{"from":66,"until":78}],"shared_borrow":[],"mutable_borrow":[],"drop":false,"drop_range":[],"must_live_at":[]},{"type":"other","local":{"id":11,"fn_id":10},"ty":"&str","lives":[{"from":84,"until":92},{"from":31,"until":36}],"shared_borrow":[],"mutable_borrow":[],"drop":false,"drop_range":[],"must_live_at":[]},{"type":"other","local":{"id":12,"fn_id":10},"ty":"&str","lives":[{"from":84,"until":92}],"shared_borrow":[],"mutable_borrow":[],"drop":false,"drop_range":[],"must_live_at":[]},{"type":"other","local":{"id":13,"fn_id":10},"ty":"&dyn std::fmt::Debug","lives":[{"from":91,"until":92},{"from":31,"until":36}],"shared_borrow":[],"mutable_borrow":[],"drop":false,"drop_range":[],"must_live_at":[]},{"type":"other","local":{"id":14,"fn_id":10},"ty":"&&i32","lives":[{"from":84,"until":92}],"shared_borrow":[],"mutable_borrow":[],"drop":false,"drop_range":[],"must_live_at":[]},{"type":"other","local":{"id":15,"fn_id":10},"ty":"&&i32","lives":[{"from":84,"until":92}],"shared_borrow":[],"mutable_borrow":[],"drop":false,"drop_range":[],"must_live_at":[]},{"type":"other","local":{"id":16,"fn_id":10},"ty":"&i32","lives":[{"from":84,"until":92}],"shared_borrow":[{"from":84,"until":92},{"from":31,"until":36}],"mutable_borrow":[],"drop":false,"drop_range":[],"must_live_at":[{"from":84,"until":92},{"from":31,"until":36}]}]},{"fn_id":19,"basic_blocks":[{"statements":[{"type":"assign","target_local":{"id":0,"fn_id":19},"range":{"from":113,"until":118},"rval":null}],"terminator":{"type":"other"}}],"decls":[{"type":"other","local":{"id":0,"fn_id":19},"ty":"Point","lives":[],"shared_borrow":[],"mutable_borrow":[],"drop":false,"drop_range":[],"must_live_at":[]},{"type":"user","local":{"id":1,"fn_id":19},"name":"self","span":{"from":113,"until":118},"ty":"&Point","lives":[{"from":113,"until":118}],"shared_borrow":[],"mutable_borrow":[],"drop":false,"drop_range":[],"must_live_at":[]}]},{"fn_id":10,"basic_blocks":[{"statements":[{"type":"assign","target_local":{"id":3,"fn_id":10},"range":{"from":31,"until":36},"rval":{"type":"borrow","target_local":{"id":2,"fn_id":10},"range":{"from":31,"until":36},"mutable":true,"outlive":null}},{"type":"assign","target_local":{"id":5,"fn_id":10},"range":{"from":31,"until":36},"rval":null},{"type":"assign","target_local":{"id":4,"fn_id":10},"range":{"from":31,"until":36},"rval":{"type":"borrow","target_local":{"id":5,"fn_id":10},"range":{"from":31,"until":36},"mutable":false,"outlive":null}},{"type":"assign","target_local":{"id":7,"fn_id":10},"range":{"from":66,"until":78},"rval":null},{"type":"assign","target_local":{"id":6,"fn_id":10},"range":{"from":66,"until":78},"rval":{"type":"borrow","target_local":{"id":7,"fn_id":10},"range":{"from":66,"until":78},"mutable":false,"outlive":null}},{"type":"assign","target_local":{"id":10,"fn_id":10},"range":{"from":66,"until":78},"rval":{"type":"borrow","target_local":{"id":1,"fn_id":10},"range":{"from":66,"until":78},"mutable":false,"outlive":null}},{"type":"assign","target_local":{"id":9,"fn_id":10},"range":{"from":66,"until":78},"rval":{"type":"borrow","target_local":{"id":10,"fn_id":10},"range":{"from":66,"until":78},"mutable":false,"outlive":null}},{"type":"assign","target_local":{"id":8,"fn_id":10},"range":{"from":66,"until":78},"rval":null},{"type":"assign","target_local":{"id":12,"fn_id":10},"range":{"from":84,"until":92},"rval":null},{"type":"assign","target_local":{"id":11,"fn_id":10},"range":{"from":84,"until":92},"rval":{"type":"borrow","target_local":{"id":12,"fn_id":10},"range":{"from":84,"until":92},"mutable":false,"outlive":null}},{"type":"assign","target_local":{"id":16,"fn_id":10},"range":{"from":84,"until":92},"rval":{"type":"borrow","target_local":{"id":1,"fn_id":10},"range":{"from":84,"until":92},"mutable":false,"outlive":null}},{"type":"assign","target_local":{"id":15,"fn_id":10},"range":{"from":84,"until":92},"rval":{"type":"borrow","target_local":{"id":16,"fn_id":10},"range":{"from":84,"until":92},"mutable":false,"outlive":null}},{"type":"assign","target_local":{"id":14,"fn_id":10},"range":{"from":84,"until":92},"rval":{"type":"borrow","target_local":{"id":15,"fn_id":10},"range":{"from":84,"until":92},"mutable":false,"outlive":null}},{"type":"assign","target_local":{"id":13,"fn_id":10},"range":{"from":84,"until":92},"rval":null}],"terminator":{"type":"call","destination_local":{"id":0,"fn_id":10},"fn_span":{"from":31,"until":36}}},{"statements":[],"terminator":{"type":"other"}},{"statements":[],"terminator":{"type":"other"}}],"decls":[{"type":"other","local":{"id":0,"fn_id":10},"ty":"std::result::Result<(), std::fmt::Error>","lives":[{"from":35,"until":36}],"shared_borrow":[],"mutable_borrow":[],"drop":false,"drop_range":[],"must_live_at":[]},{"type":"user","local":{"id":1,"fn_id":10},"name":"self","span":{"from":31,"until":36},"ty":"&Person","lives":[{"from":31,"until":36},{"from":66,"until":78},{"from":84,"until":92}],"shared_borrow":[],"mutable_borrow":[],"drop":false,"drop_range":[],"must_live_at":[]},{"type":"user","local":{"id":2,"fn_id":10},"name":"f","span":{"from":31,"until":36},"ty":"&mut std::fmt::Formatter<'_>","lives":[{"from":31,"until":36}],"shared_borrow":[],"mutable_borrow":[{"from":31,"until":36},{"from":66,"until":78},{"from":84,"until":92}],"drop":false,"drop_range":[],"must_live_at":[{"from":31,"until":36},{"from":66,"until":78},{"from":84,"until":92}]},{"type":"other","local":{"id":3,"fn_id":10},"ty":"&mut std::fmt::Formatter<'_>","lives":[{"from":31,"until":36},{"from":66,"until":78},{"from":84,"until":92}],"shared_borrow":[],"mutable_borrow":[],"drop":false,"drop_range":[],"must_live_at":[]},{"type":"other","local":{"id":4,"fn_id":10},"ty":"&str","lives":[{"from":66,"until":78},{"from":84,"until":92},{"from":31,"until":36}],"shared_borrow":[],"mutable_borrow":[],"drop":false,"drop_range":[],"must_live_at":[]},{"type":"other","local":{"id":5,"fn_id":10},"ty":"&str","lives":[{"from":31,"until":36}],"shared_borrow":[],"mutable_borrow":[],"drop":false,"drop_range":[],"must_live_at":[]},{"type":"other","local":{"id":6,"fn_id":10},"ty":"&str","lives":[{"from":66,"until":78},{"from":84,"until":92},{"from":31,"until":36}],"shared_borrow":[],"mutable_borrow":[],"drop":false,"drop_range":[],"must_live_at":[]},{"type":"other","local":{"id":7,"fn_id":10},"ty":"&str","lives":[{"from":66,"until":78}],"shared_borrow":[],"mutable_borrow":[],"drop":false,"drop_range":[],"must_live_at":[]},{"type":"other","local":{"id":8,"fn_id":10},"ty":"&dyn std::fmt::Debug","lives":[{"from":77,"until":78},{"from":84,"until":92},{"from":31,"until":36}],"shared_borrow":[],"mutable_borrow":[],"drop":false,"drop_range":[],"must_live_at":[]},{"type":"other","local":{"id":9,"fn_id":10},"ty":"&std::string::String","lives":[{"from":66,"until":78}],"shared_borrow":[],"mutable_borrow":[],"drop":false,"drop_range":[],"must_live_at":[]},{"type":"other","local":{"id":10,"fn_id":10},"ty":"&std::string::String","lives":[{"from":66,"until":78}],"shared_borrow":[],"mutable_borrow":[],"drop":false,"drop_range":[],"must_live_at":[]},{"type":"other","local":{"id":11,"fn_id":10},"ty":"&str","lives":[{"from":84,"until":92},{"from":31,"until":36}],"shared_borrow":[],"mutable_borrow":[],"drop":false,"drop_range":[],"must_live_at":[]},{"type":"other","local":{"id":12,"fn_id":10},"ty":"&str","lives":[{"from":84,"until":92}],"shared_borrow":[],"mutable_borrow":[],"drop":false,"drop_range":[],"must_live_at":[]},{"type":"other","local":{"id":13,"fn_id":10},"ty":"&dyn std::fmt::Debug","lives":[{"from":91,"until":92},{"from":31,"until":36}],"shared_borrow":[],"mutable_borrow":[],"drop":false,"drop_range":[],"must_live_at":[]},{"type":"other","local":{"id":14,"fn_id":10},"ty":"&&i32","lives":[{"from":84,"until":92}],"shared_borrow":[],"mutable_borrow":[],"drop":false,"drop_range":[],"must_live_at":[]},{"type":"other","local":{"id":15,"fn_id":10},"ty":"&&i32","lives":[{"from":84,"until":92}],"shared_borrow":[],"mutable_borrow":[],"drop":false,"drop_range":[],"must_live_at":[]},{"type":"other","local":{"id":16,"fn_id":10},"ty":"&i32","lives":[{"from":84,"until":92}],"shared_borrow":[{"from":84,"until":92},{"from":31,"until":36}],"mutable_borrow":[],"drop":false,"drop_range":[],"must_live_at":[{"from":84,"until":92},{"from":31,"until":36}]}]},{"fn_id":19,"basic_blocks":[{"statements":[{"type":"assign","target_local":{"id":0,"fn_id":19},"range":{"from":113,"until":118},"rval":null}],"terminator":{"type":"other"}}],"decls":[{"type":"other","local":{"id":0,"fn_id":19},"ty":"Point","lives":[],"shared_borrow":[],"mutable_borrow":[],"drop":false,"drop_range":[],"must_live_at":[]},{"type":"user","local":{"id":1,"fn_id":19},"name":"self","span":{"from":113,"until":118},"ty":"&Point","lives":[{"from":113,"until":118}],"shared_borrow":[],"mutable_borrow":[],"drop":false,"drop_range":[],"must_live_at":[]}]},{"fn_id":4,"basic_blocks":[{"statements":[{"type":"assign","target_local":{"id":3,"fn_id":4},"range":{"from":235,"until":236},"rval":null},{"type":"assign","target_local":{"id":4,"fn_id":4},"range":{"from":238,"until":239},"rval":null},{"type":"assign","target_local":{"id":0,"fn_id":4},"range":{"from":227,"until":241},"rval":null}],"terminator":{"type":"other"}}],"decls":[{"type":"other","local":{"id":0,"fn_id":4},"ty":"Point","lives":[{"from":240,"until":241}],"shared_borrow":[],"mutable_borrow":[],"drop":false,"drop_range":[],"must_live_at":[]},{"type":"user","local":{"id":1,"fn_id":4},"name":"x","span":{"from":193,"until":194},"ty":"i32","lives":[{"from":235,"until":236}],"shared_borrow":[],"mutable_borrow":[],"drop":false,"drop_range":[],"must_live_at":[]},{"type":"user","local":{"id":2,"fn_id":4},"name":"y","span":{"from":201,"until":202},"ty":"i32","lives":[{"from":235,"until":236},{"from":238,"until":239}],"shared_borrow":[],"mutable_borrow":[],"drop":false,"drop_range":[],"must_live_at":[]},{"type":"other","local":{"id":3,"fn_id":4},"ty":"i32","lives":[{"from":227,"until":241}],"shared_borrow":[],"mutable_borrow":[],"drop":false,"drop_range":[],"must_live_at":[]},{"type":"other","local":{"id":4,"fn_id":4},"ty":"i32","lives":[{"from":227,"until":241}],"shared_borrow":[],"mutable_borrow":[],"drop":false,"drop_range":[],"must_live_at":[]}]},{"fn_id":17,"basic_blocks":[{"statements":[{"type":"assign","target_local":{"id":3,"fn_id":17},"range":{"from":106,"until":111},"rval":{"type":"borrow","target_local":{"id":2,"fn_id":17},"range":{"from":106,"until":111},"mutable":true,"outlive":null}},{"type":"assign","target_local":{"id":5,"fn_id":17},"range":{"from":106,"until":111},"rval":null},{"type":"assign","target_local":{"id":4,"fn_id":17},"range":{"from":106,"until":111},"rval":{"type":"borrow","target_local":{"id":5,"fn_id":17},"range":{"from":106,"until":111},"mutable":false,"outlive":null}},{"type":"assign","target_local":{"id":7,"fn_id":17},"range":{"from":146,"until":152},"rval":null},{"type":"assign","target_local":{"id":6,"fn_id":17},"range":{"from":146,"until":152},"rval":{"type":"borrow","target_local":{"id":7,"fn_id":17},"range":{"from":146,"until":152},"mutable":false,"outlive":null}},{"type":"assign","target_local":{"id":10,"fn_id":17},"range":{"from":146,"until":152},"rval":{"type":"borrow","target_local":{"id":1,"fn_id":17},"range":{"from":146,"until":152},"mutable":false,"outlive":null}},{"type":"assign","target_local":{"id":9,"fn_id":17},"range":{"from":146,"until":152},"rval":{"type":"borrow","target_local":{"id":10,"fn_id":17},"range":{"from":146,"until":152},"mutable":false,"outlive":null}},{"type":"assign","target_local":{"id":8,"fn_id":17},"range":{"from":146,"until":152},"rval":null},{"type":"assign","target_local":{"id":12,"fn_id":17},"range":{"from":158,"until":164},"rval":null},{"type":"assign","target_local":{"id":11,"fn_id":17},"range":{"from":158,"until":164},"rval":{"type":"borrow","target_local":{"id":12,"fn_id":17},"range":{"from":158,"until":164},"mutable":false,"outlive":null}},{"type":"assign","target_local":{"id":16,"fn_id":17},"range":{"from":158,"until":164},"rval":{"type":"borrow","target_local":{"id":1,"fn_id":17},"range":{"from":158,"until":164},"mutable":false,"outlive":null}},{"type":"assign","target_local":{"id":15,"fn_id":17},"range":{"from":158,"until":164},"rval":{"type":"borrow","target_local":{"id":16,"fn_id":17},"range":{"from":158,"until":164},"mutable":false,"outlive":null}},{"type":"assign","target_local":{"id":14,"fn_id":17},"range":{"from":158,"until":164},"rval":{"type":"borrow","target_local":{"id":15,"fn_id":17},"range":{"from":158,"until":164},"mutable":false,"outlive":null}},{"type":"assign","target_local":{"id":13,"fn_id":17},"range":{"from":158,"until":164},"rval":null}],"terminator":{"type":"call","destination_local":{"id":0,"fn_id":17},"fn_span":{"from":106,"until":111}}},{"statements":[],"terminator":{"type":"other"}},{"statements":[],"terminator":{"type":"other"}}],"decls":[{"type":"other","local":{"id":0,"fn_id":17},"ty":"std::result::Result<(), std::fmt::Error>","lives":[{"from":110,"until":111}],"shared_borrow":[],"mutable_borrow":[],"drop":false,"drop_range":[],"must_live_at":[]},{"type":"user","local":{"id":1,"fn_id":17},"name":"self","span":{"from":106,"until":111},"ty":"&Point","lives":[{"from":106,"until":111},{"from":146,"until":152},{"from":158,"until":164}],"shared_borrow":[],"mutable_borrow":[],"drop":false,"drop_range":[],"must_live_at":[]},{"type":"user","local":{"id":2,"fn_id":17},"name":"f","span":{"from":106,"until":111},"ty":"&mut std::fmt::Formatter<'_>","lives":[{"from":106,"until":111}],"shared_borrow":[],"mutable_borrow":[{"from":106,"until":111},{"from":146,"until":152},{"from":158,"until":164}],"drop":false,"drop_range":[],"must_live_at":[{"from":106,"until":111},{"from":146,"until":152},{"from":158,"until":164}]},{"type":"other","local":{"id":3,"fn_id":17},"ty":"&mut std::fmt::Formatter<'_>","lives":[{"from":106,"until":111},{"from":146,"until":152},{"from":158,"until":164}],"shared_borrow":[],"mutable_borrow":[],"drop":false,"drop_range":[],"must_live_at":[]},{"type":"other","local":{"id":4,"fn_id":17},"ty":"&str","lives":[{"from":146,"until":152},{"from":158,"until":164},{"from":106,"until":111}],"shared_borrow":[],"mutable_borrow":[],"drop":false,"drop_range":[],"must_live_at":[]},{"type":"other","local":{"id":5,"fn_id":17},"ty":"&str","lives":[{"from":106,"until":111}],"shared_borrow":[],"mutable_borrow":[],"drop":false,"drop_range":[],"must_live_at":[]},{"type":"other","local":{"id":6,"fn_id":17},"ty":"&str","lives":[{"from":146,"until":152},{"from":158,"until":164},{"from":106,"until":111}],"shared_borrow":[],"mutable_borrow":[],"drop":false,"drop_range":[],"must_live_at":[]},{"type":"other","local":{"id":7,"fn_id":17},"ty":"&str","lives":[{"from":146,"until":152}],"shared_borrow":[],"mutable_borrow":[],"drop":false,"drop_range":[],"must_live_at":[]},{"type":"other","local":{"id":8,"fn_id":17},"ty":"&dyn std::fmt::Debug","lives":[{"from":151,"until":152},{"from":158,"until":164},{"from":106,"until":111}],"shared_borrow":[],"mutable_borrow":[],"drop":false,"drop_range":[],"must_live_at":[]},{"type":"other","local":{"id":9,"fn_id":17},"ty":"&i32","lives":[{"from":146,"until":152}],"shared_borrow":[],"mutable_borrow":[],"drop":false,"drop_range":[],"must_live_at":[]},{"type":"other","local":{"id":10,"fn_id":17},"ty":"&i32","lives":[{"from":146,"until":152}],"shared_borrow":[],"mutable_borrow":[],"drop":false,"drop_range":[],"must_live_at":[]},{"type":"other","local":{"id":11,"fn_id":17},"ty":"&str","lives":[{"from":158,"until":164},{"from":106,"until":111}],"shared_borrow":[],"mutable_borrow":[],"drop":false,"drop_range":[],"must_live_at":[]},{"type":"other","local":{"id":12,"fn_id":17},"ty":"&str","lives":[{"from":158,"until":164}],"shared_borrow":[],"mutable_borrow":[],"drop":false,"drop_range":[],"must_live_at":[]},{"type":"other","local":{"id":13,"fn_id":17},"ty":"&dyn std::fmt::Debug","lives":[{"from":163,"until":164},{"from":106,"until":111}],"shared_borrow":[],"mutable_borrow":[],"drop":false,"drop_range":[],"must_live_at":[]},{"type":"other","local":{"id":14,"fn_id":17},"ty":"&&i32","lives":[{"from":158,"until":164}],"shared_borrow":[],"mutable_borrow":[],"drop":false,"drop_range":[],"must_live_at":[]},{"type":"other","local":{"id":15,"fn_id":17},"ty":"&&i32","lives":[{"from":158,"until":164}],"shared_borrow":[],"mutable_borrow":[],"drop":false,"drop_range":[],"must_live_at":[]},{"type":"other","local":{"id":16,"fn_id":17},"ty":"&i32","lives":[{"from":158,"until":164}],"shared_borrow":[{"from":158,"until":164},{"from":106,"until":111}],"mutable_borrow":[],"drop":false,"drop_range":[],"must_live_at":[{"from":158,"until":164},{"from":106,"until":111}]}]},{"fn_id":21,"basic_blocks":[{"statements":[],"terminator":null},{"statements":[],"terminator":{"type":"other"}},{"statements":[],"terminator":{"type":"other"}}],"decls":[{"type":"other","local":{"id":0,"fn_id":21},"ty":"()","lives":[],"shared_borrow":[],"mutable_borrow":[],"drop":false,"drop_range":[],"must_live_at":[]},{"type":"other","local":{"id":1,"fn_id":21},"ty":"&[&test::TestDescAndFn]","lives":[],"shared_borrow":[],"mutable_borrow":[],"drop":false,"drop_range":[],"must_live_at":[]},{"type":"other","local":{"id":2,"fn_id":21},"ty":"&[&test::TestDescAndFn; 0]","lives":[],"shared_borrow":[],"mutable_borrow":[],"drop":false,"drop_range":[],"must_live_at":[]},{"type":"other","local":{"id":3,"fn_id":21},"ty":"&[&test::TestDescAndFn; 0]","lives":[],"shared_borrow":[],"mutable_borrow":[],"drop":false,"drop_range":[],"must_live_at":[]},{"type":"other","local":{"id":4,"fn_id":21},"ty":"[&test::TestDescAndFn; 0]","lives":[],"shared_borrow":[],"mutable_borrow":[],"drop":false,"drop_range":[],"must_live_at":[]},{"type":"other","local":{"id":5,"fn_id":21},"ty":"&[&test::TestDescAndFn; 0]","lives":[],"shared_borrow":[],"mutable_borrow":[],"drop":false,"drop_range":[],"must_live_at":[]}]},{"fn_id":5,"basic_blocks":[{"statements":[{"type":"assign","target_local":{"id":1,"fn_id":5},"range":{"from":279,"until":281},"rval":null},{"type":"assign","target_local":{"id":2,"fn_id":5},"range":{"from":295,"until":296},"rval":null},{"type":"assign","target_local":{"id":3,"fn_id":5},"range":{"from":302,"until":308},"rval":null}],"terminator":{"type":"other"}},{"statements":[{"type":"assign","target_local":{"id":1,"fn_id":5},"range":{"from":302,"until":308},"rval":{"type":"move","target_local":{"id":3,"fn_id":5},"range":{"from":302,"until":308}}},{"type":"assign","target_local":{"id":62,"fn_id":5},"range":{"from":323,"until":334},"rval":null},{"type":"assign","target_local":{"id":8,"fn_id":5},"range":{"from":323,"until":334},"rval":{"type":"borrow","target_local":{"id":62,"fn_id":5},"range":{"from":323,"until":334},"mutable":false,"outlive":null}},{"type":"assign","target_local":{"id":7,"fn_id":5},"range":{"from":323,"until":334},"rval":{"type":"borrow","target_local":{"id":8,"fn_id":5},"range":{"from":323,"until":334},"mutable":false,"outlive":null}},{"type":"assign","target_local":{"id":15,"fn_id":5},"range":{"from":336,"until":337},"rval":{"type":"borrow","target_local":{"id":2,"fn_id":5},"range":{"from":336,"until":337},"mutable":false,"outlive":null}},{"type":"assign","target_local":{"id":14,"fn_id":5},"range":{"from":336,"until":337},"rval":{"type":"borrow","target_local":{"id":15,"fn_id":5},"range":{"from":336,"until":337},"mutable":false,"outlive":null}}],"terminator":{"type":"call","destination_local":{"id":13,"fn_id":5},"fn_span":{"from":326,"until":328}}},{"statements":[{"type":"assign","target_local":{"id":18,"fn_id":5},"range":{"from":339,"until":340},"rval":{"type":"borrow","target_local":{"id":1,"fn_id":5},"range":{"from":339,"until":340},"mutable":false,"outlive":null}},{"type":"assign","target_local":{"id":17,"fn_id":5},"range":{"from":339,"until":340},"rval":{"type":"borrow","target_local":{"id":18,"fn_id":5},"range":{"from":339,"until":340},"mutable":false,"outlive":null}}],"terminator":{"type":"call","destination_local":{"id":16,"fn_id":5},"fn_span":{"from":331,"until":333}}},{"statements":[],"terminator":null},{"statements":[],"terminator":null},{"statements":[],"terminator":{"type":"call","destination_local":{"id":20,"fn_id":5},"fn_span":{"from":383,"until":403}}},{"statements":[{"type":"assign","target_local":{"id":19,"fn_id":5},"range":{"from":360,"until":427},"rval":null}],"terminator":{"type":"drop","local":{"id":20,"fn_id":5},"range":{"from":426,"until":427}}},{"statements":[{"type":"assign","target_local":{"id":22,"fn_id":5},"range":{"from":443,"until":444},"rval":{"type":"borrow","target_local":{"id":19,"fn_id":5},"range":{"from":443,"until":444},"mutable":false,"outlive":null}}],"terminator":{"type":"call","destination_local":{"id":21,"fn_id":5},"fn_span":{"from":445,"until":452}}},{"statements":[{"type":"assign","target_local":{"id":24,"fn_id":5},"range":{"from":458,"until":464},"rval":{"type":"borrow","target_local":{"id":19,"fn_id":5},"range":{"from":458,"until":464},"mutable":true,"outlive":null}},{"type":"assign","target_local":{"id":26,"fn_id":5},"range":{"from":474,"until":482},"rval":null},{"type":"assign","target_local":{"id":25,"fn_id":5},"range":{"from":474,"until":482},"rval":{"type":"borrow","target_local":{"id":26,"fn_id":5},"range":{"from":474,"until":482},"mutable":false,"outlive":null}}],"terminator":{"type":"call","destination_local":{"id":23,"fn_id":5},"fn_span":{"from":465,"until":483}}},{"statements":[{"type":"assign","target_local":{"id":61,"fn_id":5},"range":{"from":498,"until":510},"rval":null},{"type":"assign","target_local":{"id":31,"fn_id":5},"range":{"from":498,"until":510},"rval":{"type":"borrow","target_local":{"id":61,"fn_id":5},"range":{"from":498,"until":510},"mutable":false,"outlive":null}},{"type":"assign","target_local":{"id":30,"fn_id":5},"range":{"from":498,"until":510},"rval":{"type":"borrow","target_local":{"id":31,"fn_id":5},"range":{"from":498,"until":510},"mutable":false,"outlive":null}},{"type":"assign","target_local":{"id":38,"fn_id":5},"range":{"from":512,"until":513},"rval":{"type":"borrow","target_local":{"id":19,"fn_id":5},"range":{"from":512,"until":513},"mutable":false,"outlive":null}},{"type":"assign","target_local":{"id":37,"fn_id":5},"range":{"from":512,"until":513},"rval":{"type":"borrow","target_local":{"id":38,"fn_id":5},"range":{"from":512,"until":513},"mutable":false,"outlive":null}}],"terminator":{"type":"call","destination_local":{"id":36,"fn_id":5},"fn_span":{"from":499,"until":503}}},{"statements":[{"type":"assign","target_local":{"id":41,"fn_id":5},"range":{"from":515,"until":517},"rval":{"type":"borrow","target_local":{"id":21,"fn_id":5},"range":{"from":515,"until":517},"mutable":false,"outlive":null}},{"type":"assign","target_local":{"id":40,"fn_id":5},"range":{"from":515,"until":517},"rval":{"type":"borrow","target_local":{"id":41,"fn_id":5},"range":{"from":515,"until":517},"mutable":false,"outlive":null}}],"terminator":{"type":"call","destination_local":{"id":39,"fn_id":5},"fn_span":{"from":505,"until":509}}},{"statements":[],"terminator":null},{"statements":[],"terminator":null},{"statements":[],"terminator":{"type":"call","destination_local":{"id":42,"fn_id":5},"fn_span":{"from":539,"until":555}}},{"statements":[{"type":"assign","target_local":{"id":43,"fn_id":5},"range":{"from":571,"until":574},"rval":null},{"type":"assign","target_local":{"id":44,"fn_id":5},"range":{"from":580,"until":590},"rval":null}],"terminator":{"type":"other"}},{"statements":[{"type":"assign","target_local":{"id":42,"fn_id":5},"range":{"from":580,"until":590},"rval":{"type":"move","target_local":{"id":44,"fn_id":5},"range":{"from":580,"until":590}}},{"type":"assign","target_local":{"id":60,"fn_id":5},"range":{"from":605,"until":617},"rval":null},{"type":"assign","target_local":{"id":49,"fn_id":5},"range":{"from":605,"until":617},"rval":{"type":"borrow","target_local":{"id":60,"fn_id":5},"range":{"from":605,"until":617},"mutable":false,"outlive":null}},{"type":"assign","target_local":{"id":48,"fn_id":5},"range":{"from":605,"until":617},"rval":{"type":"borrow","target_local":{"id":49,"fn_id":5},"range":{"from":605,"until":617},"mutable":false,"outlive":null}},{"type":"assign","target_local":{"id":56,"fn_id":5},"range":{"from":619,"until":622},"rval":{"type":"borrow","target_local":{"id":42,"fn_id":5},"range":{"from":619,"until":622},"mutable":false,"outlive":null}},{"type":"assign","target_local":{"id":55,"fn_id":5},"range":{"from":619,"until":622},"rval":{"type":"borrow","target_local":{"id":56,"fn_id":5},"range":{"from":619,"until":622},"mutable":false,"outlive":null}}],"terminator":{"type":"call","destination_local":{"id":54,"fn_id":5},"fn_span":{"from":606,"until":610}}},{"statements":[{"type":"assign","target_local":{"id":59,"fn_id":5},"range":{"from":624,"until":627},"rval":{"type":"borrow","target_local":{"id":43,"fn_id":5},"range":{"from":624,"until":627},"mutable":false,"outlive":null}},{"type":"assign","target_local":{"id":58,"fn_id":5},"range":{"from":624,"until":627},"rval":{"type":"borrow","target_local":{"id":59,"fn_id":5},"range":{"from":624,"until":627},"mutable":false,"outlive":null}}],"terminator":{"type":"call","destination_local":{"id":57,"fn_id":5},"fn_span":{"from":612,"until":616}}},{"statements":[],"terminator":null},{"statements":[],"terminator":null},{"statements":[{"type":"assign","target_local":{"id":0,"fn_id":5},"range":{"from":261,"until":631},"rval":null}],"terminator":{"type":"drop","local":{"id":21,"fn_id":5},"range":{"from":630,"until":631}}},{"statements":[],"terminator":{"type":"drop","local":{"id":19,"fn_id":5},"range":{"from":630,"until":631}}},{"statements":[],"terminator":{"type":"other"}},{"statements":[],"terminator":{"type":"drop","local":{"id":21,"fn_id":5},"range":{"from":630,"until":631}}},{"statements":[],"terminator":{"type":"drop","local":{"id":19,"fn_id":5},"range":{"from":630,"until":631}}},{"statements":[],"terminator":{"type":"other"}}],"decls":[{"type":"other","local":{"id":0,"fn_id":5},"ty":"()","lives":[{"from":630,"until":631}],"shared_borrow":[],"mutable_borrow":[],"drop":false,"drop_range":[],"must_live_at":[]},{"type":"user","local":{"id":1,"fn_id":5},"name":"x","span":{"from":271,"until":276},"ty":"i32","lives":[{"from":271,"until":276},{"from":291,"until":292},{"from":295,"until":296},{"from":302,"until":308},{"from":323,"until":334},{"from":336,"until":337},{"from":339,"until":340}],"shared_borrow":[{"from":339,"until":340},{"from":331,"until":333}],"mutable_borrow":[],"drop":false,"drop_range":[],"must_live_at":[{"from":339,"until":340},{"from":331,"until":333}]},{"type":"user","local":{"id":2,"fn_id":5},"name":"y","span":{"from":291,"until":292},"ty":"i32","lives":[{"from":291,"until":292},{"from":302,"until":308},{"from":323,"until":334},{"from":336,"until":337}],"shared_borrow":[{"from":336,"until":337},{"from":326,"until":328},{"from":331,"until":333},{"from":339,"until":340}],"mutable_borrow":[],"drop":false,"drop_range":[],"must_live_at":[{"from":336,"until":337},{"from":326,"until":328},{"from":331,"until":333},{"from":339,"until":340}]},{"type":"other","local":{"id":3,"fn_id":5},"ty":"(i32, bool)","lives":[{"from":302,"until":308}],"shared_borrow":[],"mutable_borrow":[],"drop":false,"drop_range":[],"must_live_at":[]},{"type":"other","local":{"id":4,"fn_id":5},"ty":"()","lives":[],"shared_borrow":[],"mutable_borrow":[],"drop":false,"drop_range":[],"must_live_at":[]},{"type":"other","local":{"id":5,"fn_id":5},"ty":"()","lives":[],"shared_borrow":[],"mutable_borrow":[],"drop":false,"drop_range":[],"must_live_at":[]},{"type":"other","local":{"id":6,"fn_id":5},"ty":"std::fmt::Arguments<'_>","lives":[],"shared_borrow":[],"mutable_borrow":[],"drop":false,"drop_range":[],"must_live_at":[]},{"type":"other","local":{"id":7,"fn_id":5},"ty":"&[&str; 3]","lives":[{"from":326,"until":328},{"from":336,"until":337},{"from":331,"until":333},{"from":339,"until":340}],"shared_borrow":[],"mutable_borrow":[],"drop":false,"drop_range":[],"must_live_at":[]},{"type":"other","local":{"id":8,"fn_id":5},"ty":"&[&str; 3]","lives":[{"from":323,"until":334}],"shared_borrow":[],"mutable_borrow":[],"drop":false,"drop_range":[],"must_live_at":[]},{"type":"other","local":{"id":9,"fn_id":5},"ty":"[&str; 3]","lives":[],"shared_borrow":[],"mutable_borrow":[],"drop":false,"drop_range":[],"must_live_at":[]},{"type":"other","local":{"id":10,"fn_id":5},"ty":"&[core::fmt::rt::Argument<'_>; 2]","lives":[],"shared_borrow":[],"mutable_borrow":[],"drop":false,"drop_range":[],"must_live_at":[]},{"type":"other","local":{"id":11,"fn_id":5},"ty":"&[core::fmt::rt::Argument<'_>; 2]","lives":[],"shared_borrow":[],"mutable_borrow":[],"drop":false,"drop_range":[],"must_live_at":[]},{"type":"other","local":{"id":12,"fn_id":5},"ty":"[core::fmt::rt::Argument<'_>; 2]","lives":[],"shared_borrow":[],"mutable_borrow":[],"drop":false,"drop_range":[],"must_live_at":[]},{"type":"other","local":{"id":13,"fn_id":5},"ty":"core::fmt::rt::Argument<'_>","lives":[{"from":327,"until":328},{"from":331,"until":333},{"from":339,"until":340}],"shared_borrow":[],"mutable_borrow":[],"drop":false,"drop_range":[],"must_live_at":[]},{"type":"other","local":{"id":14,"fn_id":5},"ty":"&i32","lives":[{"from":326,"until":328}],"shared_borrow":[],"mutable_borrow":[],"drop":false,"drop_range":[],"must_live_at":[]},{"type":"other","local":{"id":15,"fn_id":5},"ty":"&i32","lives":[{"from":336,"until":337}],"shared_borrow":[],"mutable_borrow":[],"drop":false,"drop_range":[],"must_live_at":[]},{"type":"other","local":{"id":16,"fn_id":5},"ty":"core::fmt::rt::Argument<'_>","lives":[{"from":332,"until":333}],"shared_borrow":[],"mutable_borrow":[],"drop":false,"drop_range":[],"must_live_at":[]},{"type":"other","local":{"id":17,"fn_id":5},"ty":"&i32","lives":[{"from":331,"until":333}],"shared_borrow":[],"mutable_borrow":[],"drop":false,"drop_range":[],"must_live_at":[]},{"type":"other","local":{"id":18,"fn_id":5},"ty":"&i32","lives":[{"from":339,"until":340}],"shared_borrow":[],"mutable_borrow":[],"drop":false,"drop_range":[],"must_live_at":[]},{"type":"user","local":{"id":19,"fn_id":5},"name":"p","span":{"from":352,"until":357},"ty":"Person","lives":[{"from":426,"until":427},{"from":352,"until":357},{"from":438,"until":440},{"from":443,"until":452},{"from":458,"until":484},{"from":498,"until":510},{"from":512,"until":513}],"shared_borrow":[{"from":443,"until":452},{"from":512,"until":513},{"from":499,"until":503},{"from":505,"until":509},{"from":515,"until":517}],"mutable_borrow":[{"from":458,"until":483}],"drop":true,"drop_range":[{"from":261,"until":631}],"must_live_at":[{"from":443,"until":452},{"from":474,"until":482},{"from":512,"until":513},{"from":499,"until":503},{"from":505,"until":509},{"from":515,"until":517}]},{"type":"other","local":{"id":20,"fn_id":5},"ty":"std::string::String","lives":[{"from":360,"until":427}],"shared_borrow":[],"mutable_borrow":[],"drop":true,"drop_range":[],"must_live_at":[]},{"type":"user","local":{"id":21,"fn_id":5},"name":"p2","span":{"from":438,"until":440},"ty":"Person","lives":[{"from":451,"until":452},{"from":438,"until":440},{"from":458,"until":484},{"from":498,"until":510},{"from":512,"until":513},{"from":515,"until":517}],"shared_borrow":[{"from":515,"until":517},{"from":505,"until":509}],"mutable_borrow":[],"drop":true,"drop_range":[{"from":261,"until":631}],"must_live_at":[{"from":515,"until":517},{"from":505,"until":509}]},{"type":"other","local":{"id":22,"fn_id":5},"ty":"&Person","lives":[{"from":443,"until":452}],"shared_borrow":[],"mutable_borrow":[],"drop":false,"drop_range":[],"must_live_at":[]},{"type":"other","local":{"id":23,"fn_id":5},"ty":"()","lives":[],"shared_borrow":[],"mutable_borrow":[],"drop":false,"drop_range":[],"must_live_at":[]},{"type":"other","local":{"id":24,"fn_id":5},"ty":"&mut std::string::String","lives":[{"from":458,"until":483}],"shared_borrow":[],"mutable_borrow":[],"drop":false,"drop_range":[],"must_live_at":[]},{"type":"other","local":{"id":25,"fn_id":5},"ty":"&str","lives":[{"from":458,"until":483}],"shared_borrow":[],"mutable_borrow":[],"drop":false,"drop_range":[],"must_live_at":[]},{"type":"other","local":{"id":26,"fn_id":5},"ty":"&str","lives":[{"from":474,"until":482}],"shared_borrow":[],"mutable_borrow":[],"drop":false,"drop_range":[],"must_live_at":[]},{"type":"other","local":{"id":27,"fn_id":5},"ty":"()","lives":[],"shared_borrow":[],"mutable_borrow":[],"drop":false,"drop_range":[],"must_live_at":[]},{"type":"other","local":{"id":28,"fn_id":5},"ty":"()","lives":[],"shared_borrow":[],"mutable_borrow":[],"drop":false,"drop_range":[],"must_live_at":[]},{"type":"other","local":{"id":29,"fn_id":5},"ty":"std::fmt::Arguments<'_>","lives":[],"shared_borrow":[],"mutable_borrow":[],"drop":false,"drop_range":[],"must_live_at":[]},{"type":"other","local":{"id":30,"fn_id":5},"ty":"&[&str; 3]","lives":[{"from":499,"until":503},{"from":512,"until":513},{"from":505,"until":509},{"from":515,"until":517}],"shared_borrow":[],"mutable_borrow":[],"drop":false,"drop_range":[],"must_live_at":[]},{"type":"other","local":{"id":31,"fn_id":5},"ty":"&[&str; 3]","lives":[{"from":498,"until":510}],"shared_borrow":[],"mutable_borrow":[],"drop":false,"drop_range":[],"must_live_at":[]},{"type":"other","local":{"id":32,"fn_id":5},"ty":"[&str; 3]","lives":[],"shared_borrow":[],"mutable_borrow":[],"drop":false,"drop_range":[],"must_live_at":[]},{"type":"other","local":{"id":33,"fn_id":5},"ty":"&[core::fmt::rt::Argument<'_>; 2]","lives":[],"shared_borrow":[],"mutable_borrow":[],"drop":false,"drop_range":[],"must_live_at":[]},{"type":"other","local":{"id":34,"fn_id":5},"ty":"&[core::fmt::rt::Argument<'_>; 2]","lives":[],"shared_borrow":[],"mutable_borrow":[],"drop":false,"drop_range":[],"must_live_at":[]},{"type":"other","local":{"id":35,"fn_id":5},"ty":"[core::fmt::rt::Argument<'_>; 2]","lives":[],"shared_borrow":[],"mutable_borrow":[],"drop":false,"drop_range":[],"must_live_at":[]},{"type":"other","local":{"id":36,"fn_id":5},"ty":"core::fmt::rt::Argument<'_>","lives":[{"from":502,"until":503},{"from":505,"until":509},{"from":515,"until":517}],"shared_borrow":[],"mutable_borrow":[],"drop":false,"drop_range":[],"must_live_at":[]},{"type":"other","local":{"id":37,"fn_id":5},"ty":"&Person","lives":[{"from":499,"until":503}],"shared_borrow":[],"mutable_borrow":[],"drop":false,"drop_range":[],"must_live_at":[]},{"type":"other","local":{"id":38,"fn_id":5},"ty":"&Person","lives":[{"from":512,"until":513}],"shared_borrow":[],"mutable_borrow":[],"drop":false,"drop_range":[],"must_live_at":[]},{"type":"other","local":{"id":39,"fn_id":5},"ty":"core::fmt::rt::Argument<'_>","lives":[{"from":508,"until":509}],"shared_borrow":[],"mutable_borrow":[],"drop":false,"drop_range":[],"must_live_at":[]},{"type":"other","local":{"id":40,"fn_id":5},"ty":"&Person","lives":[{"from":505,"until":509}],"shared_borrow":[],"mutable_borrow":[],"drop":false,"drop_range":[],"must_live_at":[]},{"type":"other","local":{"id":41,"fn_id":5},"ty":"&Person","lives":[{"from":515,"until":517}],"shared_borrow":[],"mutable_borrow":[],"drop":false,"drop_range":[],"must_live_at":[]},{"type":"user","local":{"id":42,"fn_id":5},"name":"pnt","span":{"from":529,"until":536},"ty":"Point","lives":[{"from":529,"until":536},{"from":565,"until":568},{"from":571,"until":574},{"from":580,"until":590},{"from":605,"until":617},{"from":619,"until":622}],"shared_borrow":[{"from":619,"until":622},{"from":606,"until":610},{"from":612,"until":616},{"from":624,"until":627}],"mutable_borrow":[],"drop":false,"drop_range":[],"must_live_at":[{"from":619,"until":622},{"from":606,"until":610},{"from":612,"until":616},{"from":624,"until":627}]},{"type":"user","local":{"id":43,"fn_id":5},"name":"pn2","span":{"from":565,"until":568},"ty":"Point","lives":[{"from":565,"until":568},{"from":580,"until":590},{"from":605,"until":617},{"from":619,"until":622},{"from":624,"until":627}],"shared_borrow":[{"from":624,"until":627},{"from":612,"until":616}],"mutable_borrow":[],"drop":false,"drop_range":[],"must_live_at":[{"from":624,"until":627},{"from":612,"until":616}]},{"type":"other","local":{"id":44,"fn_id":5},"ty":"(i32, bool)","lives":[{"from":580,"until":590}],"shared_borrow":[],"mutable_borrow":[],"drop":false,"drop_range":[],"must_live_at":[]},{"type":"other","local":{"id":45,"fn_id":5},"ty":"()","lives":[],"shared_borrow":[],"mutable_borrow":[],"drop":false,"drop_range":[],"must_live_at":[]},{"type":"other","local":{"id":46,"fn_id":5},"ty":"()","lives":[],"shared_borrow":[],"mutable_borrow":[],"drop":false,"drop_range":[],"must_live_at":[]},{"type":"other","local":{"id":47,"fn_id":5},"ty":"std::fmt::Arguments<'_>","lives":[],"shared_borrow":[],"mutable_borrow":[],"drop":false,"drop_range":[],"must_live_at":[]},{"type":"other","local":{"id":48,"fn_id":5},"ty":"&[&str; 3]","lives":[{"from":606,"until":610},{"from":619,"until":622},{"from":612,"until":616},{"from":624,"until":627}],"shared_borrow":[],"mutable_borrow":[],"drop":false,"drop_range":[],"must_live_at":[]},{"type":"other","local":{"id":49,"fn_id":5},"ty":"&[&str; 3]","lives":[{"from":605,"until":617}],"shared_borrow":[],"mutable_borrow":[],"drop":false,"drop_range":[],"must_live_at":[]},{"type":"other","local":{"id":50,"fn_id":5},"ty":"[&str; 3]","lives":[],"shared_borrow":[],"mutable_borrow":[],"drop":false,"drop_range":[],"must_live_at":[]},{"type":"other","local":{"id":51,"fn_id":5},"ty":"&[core::fmt::rt::Argument<'_>; 2]","lives":[],"shared_borrow":[],"mutable_borrow":[],"drop":false,"drop_range":[],"must_live_at":[]},{"type":"other","local":{"id":52,"fn_id":5},"ty":"&[core::fmt::rt::Argument<'_>; 2]","lives":[],"shared_borrow":[],"mutable_borrow":[],"drop":false,"drop_range":[],"must_live_at":[]},{"type":"other","local":{"id":53,"fn_id":5},"ty":"[core::fmt::rt::Argument<'_>; 2]","lives":[],"shared_borrow":[],"mutable_borrow":[],"drop":false,"drop_range":[],"must_live_at":[]},{"type":"other","local":{"id":54,"fn_id":5},"ty":"core::fmt::rt::Argument<'_>","lives":[{"from":609,"until":610},{"from":612,"until":616},{"from":624,"until":627}],"shared_borrow":[],"mutable_borrow":[],"drop":false,"drop_range":[],"must_live_at":[]},{"type":"other","local":{"id":55,"fn_id":5},"ty":"&Point","lives":[{"from":606,"until":610}],"shared_borrow":[],"mutable_borrow":[],"drop":false,"drop_range":[],"must_live_at":[]},{"type":"other","local":{"id":56,"fn_id":5},"ty":"&Point","lives":[{"from":619,"until":622}],"shared_borrow":[],"mutable_borrow":[],"drop":false,"drop_range":[],"must_live_at":[]},{"type":"other","local":{"id":57,"fn_id":5},"ty":"core::fmt::rt::Argument<'_>","lives":[{"from":615,"until":616}],"shared_borrow":[],"mutable_borrow":[],"drop":false,"drop_range":[],"must_live_at":[]},{"type":"other","local":{"id":58,"fn_id":5},"ty":"&Point","lives":[{"from":612,"until":616}],"shared_borrow":[],"mutable_borrow":[],"drop":false,"drop_range":[],"must_live_at":[]},{"type":"other","local":{"id":59,"fn_id":5},"ty":"&Point","lives":[{"from":624,"until":627}],"shared_borrow":[],"mutable_borrow":[],"drop":false,"drop_range":[],"must_live_at":[]},{"type":"other","local":{"id":60,"fn_id":5},"ty":"&[&str; 3]","lives":[{"from":605,"until":617}],"shared_borrow":[],"mutable_borrow":[],"drop":false,"drop_range":[],"must_live_at":[]},{"type":"other","local":{"id":61,"fn_id":5},"ty":"&[&str; 3]","lives":[{"from":498,"until":510}],"shared_borrow":[],"mutable_borrow":[],"drop":false,"drop_range":[],"must_live_at":[]},{"type":"other","local":{"id":62,"fn_id":5},"ty":"&[&str; 3]","lives":[{"from":323,"until":334}],"shared_borrow":[],"mutable_borrow":[],"drop":false,"drop_range":[],"must_live_at":[]}]}]}}